peakpy/__init__.py
peakpy/app.py
peakpy/middleware.py
peakpy/response.py
peakpy-0.1.2.dist-info/METADATA
peakpy-0.1.2.dist-info/WHEEL
peakpy-0.1.2.dist-info/top_level.txt
peakpy-0.1.2.dist-info/RECORD
