Metadata-Version: 2.4
Name: peakpy
Version: 0.1.2
Summary: Python Web framework built for learning purposes
Home-page: https://github.com/Asadbek-Sotvoldiyev/peakpy
Author: Asadbek Sotvoldiyev
Author-email: blogasadbek@gmail.com
License: MIT
Classifier: License :: OSI Approved :: MIT License
Classifier: Programming Language :: Python
Classifier: Programming Language :: Python :: 3
Classifier: Programming Language :: Python :: 3.6
Classifier: Programming Language :: Python :: Implementation :: CPython
Classifier: Programming Language :: Python :: Implementation :: PyPy
Requires-Python: >=3.11.0
Requires-Dist: Jinja2==3.1.6
Requires-Dist: parse==1.20.2
Requires-Dist: requests==2.32.3
Requires-Dist: requests-wsgi-adapter==0.4.1
Requires-Dist: WebOb==1.8.9
Requires-Dist: whitenoise==6.9.0
Dynamic: author
Dynamic: author-email
Dynamic: classifier
Dynamic: description
Dynamic: description-content-type
Dynamic: home-page
Dynamic: license
Dynamic: requires-dist
Dynamic: requires-python
Dynamic: summary
